textual_filedrop/__init__.py
textual_filedrop/_filedrop.py
textual_filedrop/_getfiles.py
textual_filedrop/_icons.py
textual_filedrop-0.3.5.dist-info/METADATA
textual_filedrop-0.3.5.dist-info/WHEEL
textual_filedrop-0.3.5.dist-info/RECORD
