Metadata-Version: 2.1
Name: textual-filedrop
Version: 0.3.5
Summary: FileDrop widget for Textual, easily drag and drop files into your terminal apps.
Author: agmmnn
Author-email: agmmnn@gmail.com
Requires-Python: >=3.7.8,<4.0.0
Classifier: Programming Language :: Python :: 3
Classifier: Programming Language :: Python :: 3.8
Classifier: Programming Language :: Python :: 3.9
Classifier: Programming Language :: Python :: 3.10
Classifier: Programming Language :: Python :: 3.11
Requires-Dist: rich (>=13.3.2,<14.0.0)
Requires-Dist: textual (>=0.15.1,<0.16.0)
